github_release_cicd/__init__.py
github_release_cicd/__main__.py
github_release_cicd/cli.py
github_release_cicd/version.py
github_release_cicd-0.1.12.dist-info/LICENSE
github_release_cicd-0.1.12.dist-info/METADATA
github_release_cicd-0.1.12.dist-info/WHEEL
github_release_cicd-0.1.12.dist-info/entry_points.txt
github_release_cicd-0.1.12.dist-info/top_level.txt
github_release_cicd-0.1.12.dist-info/RECORD
